.coveragerc
.editorconfig
.gitignore
.travis.yml
LICENSE
README.md
pyproject.toml
requirements.txt
requirements_dev.txt
setup.cfg
setup.py
.github/workflows/python-publish.yml
democritus_random/__init__.py
democritus_random/random_wrapper.py
democritus_random/random_wrapper_temp_utils.py
democritus_random.egg-info/PKG-INFO
democritus_random.egg-info/SOURCES.txt
democritus_random.egg-info/dependency_links.txt
democritus_random.egg-info/requires.txt
democritus_random.egg-info/top_level.txt
democritus_random.egg-info/zip-safe
tests/__init__.py
tests/test_random_wrapper.py